snap/__init__.py
snap/datablock.py
snap/elements/client/__init__.py
snap/elements/client/fake.py
snap/elements/client/setId.py
snap/elements/client/sigcalc.py
snap/elements/combine/__init__.py
snap/elements/combine/buffer.py
snap/elements/combine/databuffer.py
snap/elements/combine/methods.py
snap/elements/combine/regions.py
snap/elements/process/__init__.py
snap/elements/process/smart_alert.py
snap_combine-0.9.0.dist-info/LICENSE
snap_combine-0.9.0.dist-info/METADATA
snap_combine-0.9.0.dist-info/WHEEL
snap_combine-0.9.0.dist-info/top_level.txt
snap_combine-0.9.0.dist-info/RECORD
