Metadata-Version: 2.1
Name: snap-combine
Version: 0.9.0
Summary: SuperNova Async Pipeline: combining
Author: Andrey Sheshukov
Author-email: ash@jinr.ru
Requires-Python: >=3.7
License-File: LICENSE
Requires-Dist: numpy>=1.19
Requires-Dist: snap-base>=2.0.3
Requires-Dist: sn-stat>=0.3.4
Provides-Extra: doc
Requires-Dist: sphinx; extra == "doc"
Requires-Dist: sphinx-rtd-theme; extra == "doc"
Provides-Extra: test
Requires-Dist: flake8; extra == "test"
Requires-Dist: pytest; extra == "test"
Requires-Dist: hypothesis; extra == "test"
Requires-Dist: pytest-asyncio; extra == "test"
